MANIFEST.in
README.rst
setup.py
collective/__init__.py
collective.editmodeswitcher.egg-info/PKG-INFO
collective.editmodeswitcher.egg-info/SOURCES.txt
collective.editmodeswitcher.egg-info/dependency_links.txt
collective.editmodeswitcher.egg-info/entry_points.txt
collective.editmodeswitcher.egg-info/namespace_packages.txt
collective.editmodeswitcher.egg-info/not-zip-safe
collective.editmodeswitcher.egg-info/requires.txt
collective.editmodeswitcher.egg-info/top_level.txt
collective/editmodeswitcher/__init__.py
collective/editmodeswitcher/browser.py
collective/editmodeswitcher/caching.py
collective/editmodeswitcher/config.py
collective/editmodeswitcher/configure.zcml
collective/editmodeswitcher/handlers.py
collective/editmodeswitcher/testing.py
collective/editmodeswitcher/tests/__init__.py
collective/editmodeswitcher/tests/test_caching.py
collective/editmodeswitcher/tests/test_functional.py
docs/HISTORY.txt
docs/LICENSE.GPL
docs/LICENSE.txt