Metadata-Version: 1.1
Name: collective.editmodeswitcher
Version: 1.0.3
Summary: Allows to toggle edit mode in Plone
Home-page: https://github.com/4teamwork/collective.editmodeswitcher
Author: 4teamwork AG
Author-email: mailto:info@4teamwork.ch
License: GPL2
Keywords: plone edit mode switch toggle
Platform: UNKNOWN
Classifier: Framework :: Plone
Classifier: Framework :: Plone :: 4.1
Classifier: Framework :: Plone :: 4.2
Classifier: Framework :: Plone :: 4.3
Classifier: Intended Audience :: Developers
Classifier: Topic :: Software Development :: Libraries :: Python Modules
